LICENSE.md
README.md
node_modules/@ampproject/remapping/README.md
node_modules/@babel/code-frame/README.md
node_modules/@babel/compat-data/README.md
node_modules/@babel/core/README.md
node_modules/@babel/generator/README.md
node_modules/@babel/helper-annotate-as-pure/README.md
node_modules/@babel/helper-compilation-targets/README.md
node_modules/@babel/helper-create-class-features-plugin/README.md
node_modules/@babel/helper-create-regexp-features-plugin/README.md
node_modules/@babel/helper-define-polyfill-provider/README.md
node_modules/@babel/helper-member-expression-to-functions/README.md
node_modules/@babel/helper-module-imports/README.md
node_modules/@babel/helper-module-transforms/README.md
node_modules/@babel/helper-optimise-call-expression/README.md
node_modules/@babel/helper-plugin-utils/README.md
node_modules/@babel/helper-remap-async-to-generator/README.md
node_modules/@babel/helper-replace-supers/README.md
node_modules/@babel/helper-skip-transparent-expression-wrappers/README.md
node_modules/@babel/helper-string-parser/README.md
node_modules/@babel/helper-validator-identifier/README.md
node_modules/@babel/helper-validator-option/README.md
node_modules/@babel/helper-wrap-function/README.md
node_modules/@babel/helpers/README.md
node_modules/@babel/parser/README.md
node_modules/@babel/plugin-bugfix-firefox-class-in-computed-class-key/README.md
node_modules/@babel/plugin-bugfix-safari-class-field-initializer-scope/README.md
node_modules/@babel/plugin-bugfix-safari-id-destructuring-collision-in-function-expression/README.md
node_modules/@babel/plugin-bugfix-v8-spread-parameters-in-optional-chaining/README.md
node_modules/@babel/plugin-bugfix-v8-static-class-fields-redefine-readonly/README.md
node_modules/@babel/plugin-proposal-private-property-in-object/README.md
node_modules/@babel/plugin-syntax-import-assertions/README.md
node_modules/@babel/plugin-syntax-import-attributes/README.md
node_modules/@babel/plugin-syntax-jsx/README.md
node_modules/ci-info/README.md
node_modules/hosted-git-info/README.md
picata-0.0.11.dist-info/METADATA
picata-0.0.11.dist-info/WHEEL
picata-0.0.11.dist-info/licenses/LICENSE.md
picata-0.0.11.dist-info/RECORD
