Metadata-Version: 2.4
Name: picata
Version: 0.0.11
Summary: Ada's Wagtail-based CMS & blog
Project-URL: Documentation, https://github.com/hipikat/picata#readme
Project-URL: Issues, https://github.com/hipikat/picata/issues
Project-URL: Source, https://github.com/hipikat/picata
Author-email: Ada Wright <ada@hpk.io>
License: # The MIT License (MIT)
License-File: LICENSE.md
Keywords: blog,cms,django,wagtail
Classifier: Development Status :: 2 - Pre-Alpha
Classifier: Framework :: Django CMS
Classifier: Framework :: Wagtail :: 6
Classifier: Programming Language :: Python
Classifier: Programming Language :: Python :: 3.13
Classifier: Programming Language :: Python :: Implementation :: CPython
Requires-Python: >=3.13
Requires-Dist: lxml~=5.3.0
Requires-Dist: psutil~=6.1.0
Requires-Dist: psycopg~=3.2.3
Requires-Dist: pygments~=2.18.0
Requires-Dist: python-slugify~=8.0.4
Requires-Dist: wagtail-modeladmin~=2.1.0
Requires-Dist: wagtail~=6.2
